[
  {
    "address": "0xb76d91340F5CE3577f0a056D29f6e3Eb4E88B140",
    "chainId": 239,
    "name": "TON Token",
    "symbol": "TON",
    "decimals": 9
  },
  {
    "address": "0x0000000000000000000000000000000000000348",
    "chainId": 1,
    "name": "U.S. Dollar",
    "symbol": "USD",
    "decimals": 18
  },
  {
    "address": "0xAF988C3f7CB2AceAbB15f96b19388a259b6C438f",
    "chainId": 239,
    "name": "Tether USD",
    "symbol": "USD₮",
    "decimals": 6
  },
  {
    "address": "0x61D66bC21fED820938021B06e9b2291f3FB91945",
    "chainId": 239,
    "name": "Wrapped Ether",
    "symbol": "WETH",
    "decimals": 18
  },
  {
    "address": "0xbBbBBBBbbBBBbbbBbbBbbbbBBbBbbbbBbBbbBBbB",
    "chainId": 1,
    "name": "Bitcoin",
    "symbol": "BTC",
    "decimals": 18
  },
  {
    "address": "0xD44F691aeD69fe43180B95b6F82f89c18Fb93094",
    "chainId": 239,
    "name": "Tonstakers TON",
    "symbol": "tsTON",
    "decimals": 9
  },
  {
    "address": "0xecAc9C5F704e954931349Da37F60E39f515c11c1",
    "chainId": 239,
    "name": "Lombard Staked Bitcoin",
    "symbol": "LBTC",
    "decimals": 8
  },
  {
    "address": "0x7048c9e4aBD0cf0219E95a17A8C6908dfC4f0Ee4",
    "chainId": 239,
    "name": "Coinbase Wrapped BTC",
    "symbol": "cbBTC",
    "decimals": 8
  },
  {
    "address": "0xAf368c91793CB22739386DFCbBb2F1A9e4bCBeBf",
    "chainId": 239,
    "name": "Wrapped liquid staked Ether 2.0",
    "symbol": "wstETH",
    "decimals": 18
  },
  {
    "address": "0x9eCaf80c1303CCA8791aFBc0AD405c8a35e8d9f1",
    "chainId": 239,
    "name": "KelpDao Restaked ETH",
    "symbol": "rsETH",
    "decimals": 18
  }
]