{
  "name": "RedstoneCoreOracle",
  "address": "0xEb9Ad7Ec0b11987bF4e800531FE084D6ff6F9CCd",
  "chainId": 1,
  "base": "0x6B175474E89094C44Da98b954EedeAC495271d0F",
  "quote": "0x0000000000000000000000000000000000000348",
  "feedId": "0x4441490000000000000000000000000000000000000000000000000000000000",
  "feedDecimals": 8,
  "maxStaleness": "120",
  "checks": [
    {
      "id": "ADAPTER_EXISTS",
      "severity": "HIGH",
      "message": "Successfully indexed adapter",
      "pass": true
    },
    {
      "id": "ADAPTER_REGISTRY",
      "severity": "HIGH",
      "message": "Adapter was revoked from the adapter registry at 2025-02-19T18:46:23.000Z",
      "pass": false
    },
    {
      "id": "SOURCE_CODE_PROVENANCE",
      "severity": "HIGH",
      "message": "Contract metadata hash matches a known hash",
      "pass": true
    },
    {
      "id": "DISTINCT_ASSETS",
      "severity": "HIGH",
      "message": "No duplicates found",
      "pass": true
    },
    {
      "id": "CONSISTENT_ASSET",
      "severity": "HIGH",
      "message": "Asset 0x6B175474E89094C44Da98b954EedeAC495271d0F is DAI (Dai Stablecoin) with 18 decimals",
      "pass": true
    },
    {
      "id": "CONSISTENT_ASSET",
      "severity": "HIGH",
      "message": "Asset 0x0000000000000000000000000000000000000348 is a special designator address",
      "pass": true
    }
  ],
  "label": "DAI/USD",
  "methodology": "Unknown",
  "model": "Pull",
  "provider": "RedStone Pull",
  "whitelisted": false
}